bloom_filter/__init__.py
bloom_filter/bloom_filter.py
fast_bf-1.1.1.dist-info/LICENSE
fast_bf-1.1.1.dist-info/METADATA
fast_bf-1.1.1.dist-info/WHEEL
fast_bf-1.1.1.dist-info/top_level.txt
fast_bf-1.1.1.dist-info/RECORD
