Metadata-Version: 2.1
Name: fast-bf
Version: 1.1.1
Summary: A fast bloom filter implementation in Python
Home-page: https://github.com/GuoCheng-maker/bloom_filter.git
Author: Cheng.guo
Author-email: guocheng6868@126.com
License: UNKNOWN
Platform: UNKNOWN
Classifier: Development Status :: 3 - Alpha
Classifier: Intended Audience :: Developers
Classifier: Topic :: Software Development :: Libraries
Classifier: License :: OSI Approved :: MIT License
Classifier: Programming Language :: Python :: 3
Classifier: Programming Language :: Python :: 3.6
Classifier: Programming Language :: Python :: 3.7
Classifier: Programming Language :: Python :: 3.8
Classifier: Programming Language :: Python :: 3.9
